devo_ml/modelmanager/__init__.py
devo_ml/modelmanager/_client.py
devo_ml/modelmanager/_client_factory.py
devo_ml/modelmanager/_endpoint.py
devo_ml/modelmanager/_func_facade.py
devo_ml/modelmanager/api.py
devo_ml/modelmanager/auth.py
devo_ml/modelmanager/downloader.py
devo_ml/modelmanager/engines.py
devo_ml/modelmanager/error.py
devo_ml/modelmanager/profile.py
devo_ml/modelmanager/validator.py
devo_mlmodelmanager-1.6.1.dist-info/LICENSE
devo_mlmodelmanager-1.6.1.dist-info/METADATA
devo_mlmodelmanager-1.6.1.dist-info/WHEEL
devo_mlmodelmanager-1.6.1.dist-info/RECORD
