Metadata-Version: 2.1
Name: devo-mlmodelmanager
Version: 1.6.1
Summary: A client for Devo's ML model manager
Home-page: https://github.com/DevoInc/python-mlmodelmanager-client
License: MIT
Author: Devo ML Team
Author-email: machine.learning@devo.com
Requires-Python: >=3.7,<4.0
Classifier: Development Status :: 5 - Production/Stable
Classifier: Intended Audience :: Developers
Classifier: License :: OSI Approved :: MIT License
Classifier: Operating System :: OS Independent
Classifier: Programming Language :: Python :: 3
Classifier: Programming Language :: Python :: 3.7
Classifier: Programming Language :: Python :: 3.8
Classifier: Programming Language :: Python :: 3.9
Classifier: Programming Language :: Python :: 3.10
Classifier: Programming Language :: Python :: 3.11
Classifier: Topic :: Internet :: WWW/HTTP
Classifier: Topic :: Software Development :: Libraries :: Python Modules
Requires-Dist: requests (>=2.28.2,<3.0.0)
Requires-Dist: validators (>=0.20.0,<0.21.0)
Project-URL: Documentation, https://devoinc.github.io/python-mlmodelmanager-client/
Project-URL: Repository, https://github.com/DevoInc/python-mlmodelmanager-client
